sofia/__init__.py
sofia/__main__.py
sofia/attribute_map_factory.py
sofia/entity_type.py
sofia/error_manager.py
sofia/execution_engines/__init__.py
sofia/execution_engines/buffer.py
sofia/execution_engines/low_memory_engine.py
sofia/execution_engines/parallel_engine.py
sofia/execution_engines/simple_engine.py
sofia/execution_engines/workers/__init__.py
sofia/execution_engines/workers/parallel_worker.py
sofia/execution_engines/workers/step_worker.py
sofia/resolvers/__init__.py
sofia/resolvers/attribute_resolver.py
sofia/resolvers/entity_resolver.py
sofia/resolvers/step_resolver.py
sofia/step/__init__.py
sofia/step/concrete_step.py
sofia/step/converter.py
sofia/step/extractor.py
sofia/step/step.py
sofia/step/writer.py
sofia/tools/__init__.py
sofia/tools/build.py
sofia/tools/execute.py
sofia/tools/filter.py
sofia/tools/get.py
sofia/tools/info.py
sofia/tools/resolve.py
sofia/workflow/__init__.py
sofia/workflow/entity_node.py
sofia/workflow/resolved_workflow.py
sofia/workflow/step_node.py
sofia/workflow/step_node_factory.py
sofia/workflow/step_wrapper.py
sofia/workflow_template/__init__.py
sofia/workflow_template/entity_definition_parser.py
sofia/workflow_template/entity_set.py
sofia/workflow_template/load_entity_set.py
sofia/workflow_template/load_template.py
sofia/workflow_template/template.py
sofia-1.8.1.dist-info/DESCRIPTION.rst
sofia-1.8.1.dist-info/METADATA
sofia-1.8.1.dist-info/RECORD
sofia-1.8.1.dist-info/WHEEL
sofia-1.8.1.dist-info/entry_points.txt
sofia-1.8.1.dist-info/metadata.json
sofia-1.8.1.dist-info/top_level.txt
templates/__init__.py
templates/genomics/__init__.py
templates/genomics/entities.json
templates/genomics/attributes/__init__.py
templates/genomics/attributes/chromosome_id.py
templates/genomics/attributes/sync.py
templates/genomics/data/Emolwt.dat
templates/genomics/data/gc.prt
templates/genomics/steps/__init__.py
templates/genomics/steps/bed.py
templates/genomics/steps/chromosome_sequence.py
templates/genomics/steps/coding_sequence.py
templates/genomics/steps/cut.py
templates/genomics/steps/drug_id.py
templates/genomics/steps/fasta.py
templates/genomics/steps/gbk.py
templates/genomics/steps/gene_goterm_map.py
