Metadata-Version: 2.0
Name: sofia
Version: 1.8.1
Summary: Software for the Flexible Integration of Annotation
Home-page: https://github.com/childsish/sofia
Author: Liam H. Childs
Author-email: liam.h.childs@gmail.com
License: LICENSE.txt
Platform: UNKNOWN
Classifier: Development Status :: 5 - Production/Stable
Classifier: Intended Audience :: Science/Research
Classifier: Topic :: Scientific/Engineering :: Bio-Informatics
Requires-Dist: lhc-python (==2.0.3)
